afrr_remuneration/__init__.py
afrr_remuneration/aFRR.py
afrr_remuneration/data.py
afrr_remuneration/test_validation.py
afrr_remuneration-0.0.1.dist-info/LICENSE.md
afrr_remuneration-0.0.1.dist-info/WHEEL
afrr_remuneration-0.0.1.dist-info/METADATA
afrr_remuneration-0.0.1.dist-info/RECORD
