Metadata-Version: 2.1
Name: afrr-remuneration
Version: 0.0.1
Summary: Calculate aFRR remuneration in resolution of seconds
Home-page: https://github.com/energy2market/afrr-remuneration
License: MIT
Author: Guido Pleßmann
Author-email: guido.plessmann@e2m.energy
Requires-Python: >=3.8,<4.0
Classifier: License :: OSI Approved :: MIT License
Classifier: Programming Language :: Python :: 3
Classifier: Programming Language :: Python :: 3.10
Classifier: Programming Language :: Python :: 3.8
Classifier: Programming Language :: Python :: 3.9
Requires-Dist: pandas (>=1.3.4,<2.0.0)
Requires-Dist: poetry-dynamic-versioning (>=0.13.1,<0.14.0)
Requires-Dist: pytest (>=6.2.5,<7.0.0)
Project-URL: Repository, https://github.com/energy2market/afrr-remuneration
